README.md
setup.py
QUBO2Ising/QUBO2Ising.py
QUBO2Ising/__init__.py
QUBO2Ising.egg-info/PKG-INFO
QUBO2Ising.egg-info/SOURCES.txt
QUBO2Ising.egg-info/dependency_links.txt
QUBO2Ising.egg-info/not-zip-safe
QUBO2Ising.egg-info/top_level.txt