Metadata-Version: 1.2
Name: QUBO2Ising
Version: 0.1.1
Summary: Generate Ising model from a QUBO array.
Home-page: UNKNOWN
Author: Saptarshi Chakrabarti
Author-email: csaptarshi@pm.me
License: UNKNOWN
Project-URL: GitHub, https://github.com/csap7
Platform: UNKNOWN
